elixir/__init__.py
elixir/arterialNetwork.py
elixir/artery.py
elixir/solver.py
elixir/utils.py
elixir/cantorProject/__init__.py
elixir/cantorProject/network.py
elixir/cantorProject/sci_trainer.py
elixir/cantorProject/tfp_trainer.py
simelixir/__init__.py
simelixir/arterialNetwork.py
simelixir/artery.py
simelixir/solver.py
simelixir/utils.py
simelixir/cantorProject/__init__.py
simelixir/cantorProject/network.py
simelixir/cantorProject/sci_trainer.py
simelixir/cantorProject/tfp_trainer.py
simelixir-0.0.1.dist-info/LICENSE
simelixir-0.0.1.dist-info/METADATA
simelixir-0.0.1.dist-info/WHEEL
simelixir-0.0.1.dist-info/top_level.txt
simelixir-0.0.1.dist-info/RECORD
