Metadata-Version: 2.1
Name: simelixir
Version: 0.0.1
Summary: A Python package for 1-D blood flow simulation
Home-page: https://github.com/VANRao-Stack/
Author: Sanaul Shaheer, V Abhijith Narayan Rao
Author-email: sanaulshaheer@gmail.com
License: UNKNOWN
Platform: UNKNOWN
Classifier: Development Status :: 3 - Alpha
Classifier: Intended Audience :: Healthcare Industry
Classifier: Programming Language :: Python
Classifier: Topic :: Scientific/Engineering
Requires-Python: >=3.6
Requires-Dist: tensorflow (>=2.4.0)
Requires-Dist: tensorflow-probability (>=0.12.0)
Requires-Dist: numpy (>=1.19.4)
Requires-Dist: scipy (>=1.4.1)
Requires-Dist: plotly
